Workbook

Sheet Tổng quan
A1: Amazon PPC Automation — Rule v3.2 và test case
A2: Tài liệu tổng hợp rule hiện tại và kết quả kiểm thử trên simulator. Số liệu tổng hợp bên dưới tự tính từ các sheet.
A4: Chỉ số | B4: Giá trị | C4: Nguồn
A5: Số rule | B5: =COUNTA(Rule!B5:B28) | C5: Sheet Rule
A6: Rule có thay đổi ở v3.2 | B6: =COUNTA(Rule!L5:L28) | C6: Dòng tô xanh lá ở sheet Rule
A7: Số test case golden/edge/đối chứng | B7: ='Test case'!A43 | C7: Sheet Test case
A8: — PASS | B8: =COUNTIF('Test case'!I5:I41,"PASS") | C8: GOLDEN/INVARIANT đạt
A9: — ĐO ĐƯỢC (MEASURE) | B9: =COUNTIF('Test case'!I5:I41,"ĐO ĐƯỢC") | C9: Chỉ đo số liệu
A10: — PHÁT HIỆN vấn đề spec | B10: =COUNTIF('Test case'!I5:I41,"PHÁT HIỆN") | C10: Đo được vấn đề của spec
A11: Số unit test | B11: =COUNTA('Unit test'!C5:C346) | C11: Sheet Unit test
A12: — PASS | B12: =COUNTIF('Unit test'!D5:D346,"PASS")
A13: Tỷ lệ unit test PASS | B13: =IFERROR(B12/B11,0)
A14: Đề xuất v3.2 được đưa vào | B14: =COUNTIF('Thử nghiệm v3.2'!F5:F11,"Đưa vào*") | C14: Sheet Thử nghiệm v3.2
A17: Các sheet
A18: Rule | B18: 24 rule R01–R21B: điều kiện, hành động, lịch, cửa sổ, cooldown, ưu tiên, thay đổi v3.2
A19: Tham số G1 | B19: Máy tính ngưỡng theo sản phẩm: nhập giá, BE, CVR → tự ra T_win, T_ok, T_bad, CPA, Spend_zero, N2, N3, Bid_max
A20: Thang budget | B20: Các bậc budget $5 → $25
A21: Nguyên tắc G1-G8 | B21: Nguyên tắc chung áp cho mọi rule
A22: Test case | B22: Golden test theo spec, edge case A1–E6, đối chứng đo lường, kết quả thực tế
A23: Unit test | B23: Toàn bộ unit test tự động của simulator
A24: Thử nghiệm v3.2 | B24: Kết quả 7 đề xuất thay đổi rule và quyết định
A26: Ghi chú màu
A27: Chữ xanh dương, nền vàng | B27: Ô nhập liệu (sheet Tham số G1)
A28: Nền xanh lá nhạt | B28: Rule có thay đổi ở v3.2
A29: PASS | B29: Test đạt
A30: ĐO ĐƯỢC | B30: Test chỉ đo số liệu
A31: PHÁT HIỆN / THUA | B31: Vấn đề của spec hoặc đề xuất không đạt

Sheet Rule
A1: Danh sách rule — Amazon PPC Automation v3.2
A2: Dòng tô xanh lá là rule có thay đổi ở v3.2 so với v3.1. Nguồn: docs/simulator/spec-v3.2.md
A4: Nhóm | B4: Rule | C4: Tên | D4: Điều kiện kích hoạt | E4: Hành động | F4: Lịch chạy | G4: Cửa sổ dữ liệu | H4: Cooldown sau khi chạy | I4: Bị chặn khi tag | J4: Thứ tự ưu tiên trong nhóm (1 = cao nhất) | K4: Áp giới hạn bid G6 | L4: Thay đổi ở v3.2
A5: Campaign | B5: R01 | C5: Khởi tạo / bật lại campaign | D5: Campaign mới, hoặc người dùng bật lại campaign đã bị pause (PAUSED_AUTO chỉ bật lại khi người dùng xác nhận) | E5: Budget $5, tag NORMAL, xóa thông tin tag cũ, reset cửa sổ đo, bắt đầu 3 ngày ân hạn | F5: Hằng ngày | G5: — | H5: — | I5: — | J5: — | K5: Không
A6: Campaign | B6: R02 | C6: Tăng budget $5 → $8 | D6: Tag NORMAL, budget $5, W3 có ≥1 đơn, ACoS < T_ok | E6: Budget $8, ghi ACoS nền | F6: Hằng ngày | G6: W3 (cần đủ 3 ngày chín sau lần đổi) | H6: Budget 2 ngày | I6: MANAGE, ALERT, PAUSED_AUTO | J6: 10 | K6: Không
A7: Campaign | B7: R03 | C7: Tăng budget $8 → $10 | D7: Tag NORMAL, budget $8, W3 có ≥2 đơn, ACoS < T_ok | E7: Budget $10, ghi ACoS nền | F7: Hằng ngày | G7: W3 | H7: Budget 2 ngày | I7: MANAGE, ALERT, PAUSED_AUTO | J7: 9 | K7: Không
A8: Campaign | B8: R04 | C8: Tăng budget $10 → $12 | D8: Tag NORMAL, budget $10, cả 3 ngày đều có ≥1 đơn, ACoS < T_ok | E8: Budget $12, ghi ACoS nền | F8: Hằng ngày | G8: W3 | H8: Budget 2 ngày | I8: MANAGE, ALERT, PAUSED_AUTO | J8: 8 | K8: Không
A9: Campaign | B9: R04B | C9: Tăng budget vượt $12 (×1.2) | D9: Tag NORMAL, budget ≥ $12, tiêu ≥90% budget ở ≥5/7 ngày, W7 có ≥5 đơn, ACoS < T_win | E9: Budget ×1.2 theo thang, tối đa $25 (đã $25 thì không làm gì) | F9: Hằng ngày | G9: W7 (cần đủ 7 ngày chín sau lần tăng trước) | H9: Budget 3 ngày | I9: MANAGE, ALERT, PAUSED_AUTO | J9: 7 | K9: Không | L9: P7: ghi rõ thực tế khoảng 8 ngày lịch giữa hai lần tăng (chỉ sửa câu chữ)
A10: Campaign | B10: R05 | C10: Giảm budget | D10: Budget > $5 và một trong hai: (A) W3 có ≥1 đơn và ACoS ≥ T_bad; (B) W3 có 0 đơn và chi tiêu ≥ min(CPA_target, 0.6×Spend_zero) | E10: (A) hạ 1 bậc; (B) về thẳng $5 | F10: Hằng ngày | G10: W3 | H10: Budget 2 ngày | I10: PAUSED_AUTO | J10: 4 | K10: Không
A11: Campaign | B11: R06 | C11: Dừng khẩn cấp (Safety Stop) | D11: Từ lần reset gần nhất (tối đa 14 ngày) có 0 đơn, và: chi tiêu ≥ Spend_zero và click ≥ N2; hoặc chi tiêu ≥ min(2.5×Spend_zero, $63) | E11: PAUSE vĩnh viễn, budget $5, tag PAUSED_AUTO, gửi thông báo | F11: Hằng ngày | G11: W_post ≤ 14 ngày | H11: — | I11: PAUSED_AUTO | J11: 1 | K11: Không | L11: P4: không chạy trên campaign nguồn trong 7 ngày sau khi R15 thêm negative (ân hạn harvest)
A12: Campaign | B12: R06B | C12: Dừng campaign lỗ kéo dài | D12: W14 có ≥1 đơn, chi tiêu ≥ Spend_zero, ACoS > 1.5×BE | E12: Bước 1: lưu bậc budget, gắn MANAGE (giữ ALERT nếu có), budget $5, bid −20%. Bước 2 (sau 7 ngày): nếu ACoS W7 vẫn > 1.5×BE thì PAUSE; nếu không thì giữ tag cho R09 xử lý | F12: Hằng ngày | G12: W14 lịch; bước 2 dùng W7 sau bước 1 | H12: Budget 2 ngày, bid 3 ngày | I12: PAUSED_AUTO | J12: 2 | K12: Có
A13: Campaign | B13: R07 | C13: Gắn tag MANAGE (cảnh báo nhẹ) | D13: Tag NORMAL, W7 có ≥1 đơn và ≥10 click, ACoS_W7 > max(1.1×ACoS nền, T_win); ACoS nền = min(baseline, T_ok) | E13: Gắn MANAGE, lưu bậc budget, budget = min(hiện tại, $8), bid −10% một lần (tổng giảm do tag ≤ 30%) | F13: Mỗi 3 ngày | G13: W7 | H13: Budget 3 ngày, bid 3 ngày | I13: PAUSED_AUTO | J13: 5 | K13: Có
A14: Campaign | B14: R08 | C14: Gắn tag ALERT (cảnh báo khẩn) | D14: W3 có 0 đơn, chi tiêu ≥ 0.6×Spend_zero, 30 ngày qua từng có đơn, tag chưa phải ALERT | E14: Gắn ALERT (thay MANAGE), budget $5, lưu bậc budget nếu đang NORMAL, gửi thông báo khẩn. Không đổi bid. R06 thắng nếu cùng khớp | F14: Hằng ngày (v3.1: mỗi 3 ngày) | G14: W3 | H14: Budget 3 ngày | I14: PAUSED_AUTO | J14: 3 | K14: Không | L14: P3: chạy hằng ngày; lưu ý kiểm tra độ trễ attribution trước khi bật
A15: Campaign | B15: R09 | C15: Gỡ tag (khôi phục NORMAL) | D15: MANAGE: ACoS W7 ≤ max(ACoS nền, 0.9×T_win), ≥1 đơn, đạt 2 lần kiểm tra liên tiếp, tag tồn tại ≥6 ngày. ALERT: W7 có ≥2 đơn và ACoS ≤ T_ok | E15: Gỡ tag, budget về bậc đã lưu (không vượt), bid +10% mỗi 3 ngày đến khi hết phần giảm do tag, ghi ACoS nền mới | F15: Mỗi 3 ngày | G15: W7 | H15: Budget 3 ngày, bid 3 ngày | I15: PAUSED_AUTO | J15: 6 | K15: Có
A16: Target | B16: R13 | C16: PAUSE từ khóa "chảy máu" | D16: W14 có ≥30 click, 0 đơn, chi tiêu ≥ 2×CPA_target, và: đã bị R12 giảm và từ đó thêm ≥10 click vẫn 0 đơn; hoặc bid đang ở sàn max($0.20, 0.5×anchor) | E16: PAUSE từ khóa/target vĩnh viễn | F16: Hằng ngày | G16: W14 lịch | H16: — | I16: — | J16: 1 | K16: Không
A17: Target | B17: R12 | C17: Giảm bid từ khóa không hiệu quả | D17: W_post (tối đa 14 ngày) có ≥20 click và 0 đơn; bid chưa ở sàn | E17: Bid ×0.8 (không dưới sàn), cờ lãng phí 14 ngày (chặn R14), tăng bộ đếm R12 | F17: Hằng ngày | G17: W_post ≤ 14 ngày | H17: Bid 5 ngày | I17: — | J17: 2 | K17: Có
A18: Target | B18: R11 | C18: Giảm bid từ khóa ACoS cao | D18: W_post có ≥15 click, ≥1 đơn, ACoS > T_ok | E18: Bid × max(T_ok/ACoS, 0.8), không dưới sàn | F18: Hằng ngày | G18: W_post | H18: Bid 3 ngày | I18: — | J18: 3 | K18: Có
A19: Target | B19: R10 | C19: Tăng bid từ khóa thắng | D19: Campaign NORMAL, W14 có ≥3 đơn và ACoS ≤ T_win, W_post (≥3 ngày, ≥15 click) ACoS ≤ T_win | E19: Bid ×1.10, không vượt min(Bid_max, 2×anchor) | F19: Hằng ngày | G19: W14 lịch + W_post | H19: Bid 3 ngày | I19: MANAGE, ALERT | J19: 4 | K19: Có
A20: Target | B20: R14 | C20: Tăng bid từ khóa ít hiển thị | D20: W7 < 100 impression, bid < min($0.75, Bid_max), NORMAL, không có cờ lãng phí, không thuộc (≥10 click và 0 đơn) | E20: Bid ×1.15; tối đa 3 lần, cách nhau ≥7 ngày; sau đó cờ ít hiển thị 30 ngày | F20: Hằng ngày | G20: W7 lịch | H20: Bid 7 ngày | I20: MANAGE, ALERT | J20: 5 | K20: Có
A21: Search term | B21: R15 | C21: Thu hoạch từ khóa tốt (harvest) | D21: Search term từ Auto/Broad/Phrase, W14 có ≥2 đơn, ACoS ≤ T_ok, Exact chưa tồn tại | E21: (i) Tạo Exact trong campaign Manual, bid = CPC TB 14 ngày kẹp [$0.20, Bid_max]; (ii) chỉ khi (i) thành công và đã kiểm tra lại mới thêm Negative Exact vào nguồn | F21: Chủ Nhật | G21: W14 lịch | H21: — | I21: — | J21: 1 | K21: Có | L21: P4: ngày ghi negative là ngày 0, campaign nguồn được 7 ngày ân hạn khỏi R06
A22: Search term | B22: R16 | C22: Chặn search term nhiều click không ra đơn | D22: W14 có ≥30 click và 0 đơn (trừ khi trùng một Exact đang chạy) | E22: Thêm Negative Exact (kiểm tra trùng trước) | F22: Hằng ngày | G22: W14 lịch | H22: — | I22: — | J22: 2 | K22: Không
A23: Search term | B23: R17 | C23: Chặn search term tốn tiền không ra đơn | D23: W14 chi tiêu ≥ 2.5×CPA_target, ≥12 click, 0 đơn (cùng ngoại lệ R16) | E23: Thêm Negative Exact | F23: Hằng ngày | G23: W14 lịch | H23: — | I23: — | J23: 3 | K23: Không
A24: Placement | B24: R19 | C24: Giảm Top of Search | D24: Top W14 có ≥20 click, ACoS > T_bad (0 đơn có chi tiêu cũng tính), chi tiêu Top ≥ 2×CPA_target, boost > 0 | E24: ToS −20 điểm (thấp nhất 0) | F24: Hằng ngày | G24: W14 | H24: Placement 7 ngày | I24: — | J24: 1 | K24: Không
A25: Placement | B25: R18 | C25: Tăng Top of Search | D25: NORMAL; Top W14 ≥30 click, ≥3 đơn; CVR Top ≥ 2× phần còn lại (phần còn lại <30 click thì so CVR campaign); ACoS Top ≤ T_win | E25: ToS +10 điểm (tối đa 100%), phải thỏa trần G6 | F25: Hằng ngày | G25: W14 | H25: Placement 7 ngày | I25: MANAGE, ALERT | J25: 2 | K25: Có
A26: Theo giờ | B26: R20 | C26: Giảm bid giờ yếu | D26: Giờ H có ≥40 click trong 28 ngày và CVR giờ < 0.5×CVR campaign | E26: Bid giờ H = base × 0.70 (không dưới 0.5×base và $0.20). Bỏ qua target PAUSED | F26: Hàng tuần + theo khung giờ | G26: 28 ngày theo giờ | H26: — | I26: — | J26: 1 | K26: Có | L26: P6: bỏ ngày giờ H bị cạn budget; chỉ học khi ≥20 ngày sạch
A27: Theo giờ | B27: R21 | C27: Tăng bid giờ mạnh | D27: Giờ H có ≥40 click, ≥2 đơn, CVR giờ ≥ 1.3×CVR campaign, CVR campaign > 0, NORMAL | E27: Bid giờ H = base × 1.15 (không vượt Bid_max). Bỏ qua target PAUSED | F27: Hàng tuần + theo khung giờ | G27: 28 ngày theo giờ | H27: — | I27: MANAGE, ALERT | J27: 2 | K27: Có | L27: P6: như R20
A28: Theo giờ | B28: R21B | C28: Trả bid khi hết khung giờ | D28: Kết thúc mỗi khung giờ | E28: Bid = base × hệ số khung kế tiếp (không có thì ×1.0). Chỉ gọi API 1 lần tại ranh giới | F28: Mỗi ranh giới giờ | G28: — | H28: — | I28: — | J28: 3 | K28: Có

Sheet Tham số G1
A1: Tham số theo sản phẩm (G1) — tự tính
A2: Nhập 3 ô màu vàng (chữ xanh dương); mọi ngưỡng bên dưới tự tính lại. Ví dụ mặc định: sản phẩm $30, BE 40%, CVR 10%.
A4: Đầu vào | B4: Giá trị | C4: Ghi chú
A5: Giá bán (Price) | B5: 30 | C5: Nhập giá bán của ASIN
A6: ACoS hòa vốn (BE) | B6: 0.4 | C6: Nhập dạng phần trăm
A7: Tỷ lệ chuyển đổi kỳ vọng (Exp_CVR) | B7: 0.1 | C7: Mặc định 10% theo spec
A9: Tham số | B9: Giá trị | C9: Công thức (spec) | D9: Ý nghĩa
A10: T_win | B10: =MIN(0.3,0.7*B6) | C10: min(30%, 0.7×BE) | D10: ACoS TỐT — lãi thoải mái
A11: T_ok | B11: =MIN(0.4,0.9*B6) | C11: min(40%, 0.9×BE) | D11: ACoS chấp nhận được
A12: T_bad | B12: =MIN(0.5,1.1*B6) | C12: min(50%, 1.1×BE) | D12: ACoS tệ — sắp lỗ
A13: CPA_target | B13: =B5*B10 | C13: Price × T_win | D13: Tối đa tiền quảng cáo cho 1 đơn
A14: Spend_zero | B14: =MIN(40,MAX(10,2.5*B13)) | C14: 2.5 × CPA_target, kẹp $10–$40 | D14: Tiêu bấy nhiêu mà 0 đơn là "đốt tiền"
A15: N2 | B15: =ROUNDUP(2/B7,0) | C15: 2 ÷ Exp_CVR, làm tròn lên | D15: Click tối thiểu để kết luận "chưa ra đơn là có vấn đề"
A16: N3 | B16: =ROUNDUP(3/B7,0) | C16: 3 ÷ Exp_CVR | D16: Click để kết luận chắc hơn
A17: N2h | B17: =ROUNDUP(B15/2,0) | C17: N2 ÷ 2 | D17: Một nửa N2
A18: N17 | B18: =ROUNDUP(0.6*B15,0) | C18: 0.6 × N2 | D18: Dùng cho R17
A19: Bid_min | B19: 0.2 | C19: Cố định $0.20 | D19: Bid thấp nhất
A20: Bid_max | B20: =MAX(0.2,MIN(3,B5*B7*B11)) | C20: max($0.20, min($3, Price × CVR × T_ok)) | D20: Bid cao nhất được phép
A21: Cảnh báo sản phẩm | B21: =IF(MIN(3,B5*B7*B11)<0.2,"Không khả thi ở bid tối thiểu","OK") | C21: Bid_max tính ra < $0.20 thì cảnh báo | D21: Theo spec Phần 1
A23: Kiểm tra với ví dụ chuẩn của spec ($30, BE 40%, CVR 10%): T_win 28%, T_ok 36%, T_bad 44%, CPA $8.40, Spend_zero $21, N2 20, N3 30, Bid_max $1.08.

Sheet Thang budget
A1: Thang budget campaign
A2: Từ $12 trở lên mỗi bậc ×1.2, tối đa $25. Bậc $24.88 lấy theo spec (tính lại từ $20.74 sẽ ra $24.89).
A4: Bậc | B4: Budget ($/ngày) | C4: Rule đưa lên bậc này | D4: Cách tính
A5: 0 | B5: 5 | C5: R01 (khởi tạo), R05B, R06, R06B, R08 | D5: Cố định
A6: 1 | B6: 8 | C6: R02 | D6: Cố định
A7: 2 | B7: 10 | C7: R03 | D7: Cố định
A8: 3 | B8: 12 | C8: R04 | D8: Cố định
A9: 4 | B9: =ROUND(B8*1.2,2) | C9: R04B | D9: Bậc trước × 1.2
A10: 5 | B10: =ROUND(B9*1.2,2) | C10: R04B | D10: Bậc trước × 1.2
A11: 6 | B11: =ROUND(B10*1.2,2) | C11: R04B | D11: Bậc trước × 1.2
A12: 7 | B12: 24.88 | C12: R04B | D12: Theo spec (×1.2 từ $20.74 cho $24.89)
A13: 8 | B13: =MIN(25,ROUND(B12*1.2,2)) | C13: R04B | D13: Trần $25

Sheet Nguyên tắc G1-G8
A1: Nguyên tắc chung G1–G8
A2: Áp dụng cho mọi rule
A4: Mã | B4: Nguyên tắc | C4: Nội dung
A5: G1 | B5: Tham số theo sản phẩm | C5: Mọi ngưỡng tính theo giá bán, BE và CVR của từng ASIN (xem sheet Tham số G1); không dùng con số cố định.
A6: G2 | B6: Chỉ dùng dữ liệu đã chín | C6: Cửa sổ W3/W7/W14 kết thúc ở D-2. "0 đơn" chỉ đúng khi D-3 lẫn D-2 đều không có đơn. Sau mỗi lần thay đổi chỉ tính dữ liệu từ sau lần đó (W_post, tối đa 30 ngày). Rule 3 ngày cần đủ 3 ngày chín, rule 7 ngày cần đủ 7 ngày chín.
A7: G3 | B7: Reset, cooldown, ân hạn | C7: Đổi bid/budget/placement thì reset cửa sổ. Thay đổi không đổi giá trị thì không reset, không tính cooldown. Cooldown: bid 3 ngày (5 sau R12), budget 2 ngày, placement 7 ngày. Campaign mới/bật lại có 3 ngày ân hạn: R02–R09 không chạy.
A8: G4 | B8: Bộ nhớ hệ thống | C8: Campaign: tag, bậc budget, bậc trước khi gắn tag, ACoS nền, các mốc thời gian, giai đoạn R06B, số lần R09 đạt, % ToS, [v3.2] ngày hết ân hạn harvest. Target: base_bid, anchor_bid, hệ số giảm do tag, hệ số giờ, các cờ, bộ đếm R12/R14. Bid gửi lên = base_bid × hệ số giờ.
A9: G5 | B9: Mỗi lần chạy chỉ 1 hành động | C9: Rule đứng trước thắng (thứ tự xem sheet Rule). Rule chỉ "khớp" khi thực sự đổi được giá trị; không đổi thì nhường rule sau.
A10: G6 | B10: Giới hạn bid | C10: Mỗi lần đổi base_bid tối đa ±20% (R20/R21/R21B không bị giới hạn này). $0.20 ≤ bid ≤ Bid_max. Bid × (1 + ToS%) ≤ 1.5 × Bid_max. base_bid trong [0.5×, 2×] anchor_bid.
A11: G7 | B11: Gọi API an toàn | C11: Xóa tag cũ bằng regex trước khi gắn tag mới, không có tag kép. Kiểm tra trùng trước khi tạo keyword/negative. ALERT > MANAGE, không ghi đè ALERT bằng MANAGE. Keyword dùng /sp/keywords, Auto/Product dùng /sp/targets.
A12: G8 | B12: Múi giờ | C12: Mọi giờ chạy và ngày tính theo giờ marketplace (Mỹ = Pacific), không theo giờ Hà Nội.

Sheet Test case
A1: Test case — golden, edge case và đối chứng
A2: GOLDEN/INVARIANT: phải đúng, test fail nếu sai. MEASURE: đo và ghi số liệu. Kết quả thực tế lấy từ lần chạy simulator ngày 21/10/2026.
A4: Mã | B4: Nhóm | C4: Tên test | D4: Rule liên quan | E4: Kịch bản | F4: Kết quả mong đợi | G4: Kết quả thực tế | H4: Loại | I4: Trạng thái | J4: Nguồn (file)
A5: GT-01 | B5: Golden (spec Phần 10) | C5: Campaign thắng | D5: R01, R02, R03, R04, R04B | E5: Sản phẩm $30/BE 40%; mỗi ngày tiêu hết budget, 2 đơn, ACoS 20% | F5: R02 ngày 4 ($8), R03 ngày 8 ($10), R04 ngày 12 ($12), R04B ngày 20/28/36 | G5: Đúng: 4/8/12/20/28/36; budget $8 → $10 → $12 → $14.40 → $17.28 → $20.74 | H5: GOLDEN | I5: PASS | J5: test/campaign-loop.test.ts
A6: GT-02 | B6: Golden (spec Phần 10) | C6: Campaign 0 đơn | D6: R01, R06 | E6: $5/ngày, 5 click/ngày, 0 đơn | F6: R06 PAUSE khoảng ngày 7, gửi thông báo, giữ PAUSED | G6: R06 ngày 6 (ngày 0–4 đủ $25 và 25 click), có thông báo R06_PAUSED, giữ PAUSED đến hết | H6: GOLDEN | I6: PASS | J6: test/campaign-loop.test.ts
A7: GT-03 | B7: Golden (spec Phần 10) | C7: Xấu đi rồi hồi phục | D7: R07, R09 | E7: Đạt $12 rồi ACoS 40% (≥1 đơn/ngày), sau đó về 18% | F7: R07 gắn MANAGE, budget ≤ $8, bid −10%; R09 gỡ tag sau 2 lần đạt; bid +10% mỗi 3 ngày | G7: R07 ngày 21 ($8, bid ×0.9); R09 ngày 33 về $12; khôi phục bid ngày 36 (×0.99) và 39 (×1.0); không có R05 | H7: GOLDEN | I7: PASS | J7: test/campaign-loop.test.ts
A8: GT-04 | B8: Golden | C8: ALERT rồi pause | D8: R08, R06 | E8: Đạt $12, sau đó 0 đơn, $5/ngày | F8: R08 gắn ALERT, budget $5; nếu vẫn 0 đơn thì R06 PAUSE | G8: R08 ngày 18 ($5, ALERT), R06 ngày 24 PAUSED_AUTO; thông báo R08_ALERT, R06_PAUSED | H8: GOLDEN | I8: PASS | J8: test/campaign-loop.test.ts
A9: GT-05 | B9: Golden | C9: ALERT rồi hồi phục | D9: R08, R09 | E9: Như GT-04 nhưng ra đơn lại từ ngày 18 | F9: R09 gỡ ALERT, budget về bậc đã lưu ($12) | G9: R08 ngày 18, R09 ngày 27 về $12 NORMAL | H9: GOLDEN | I9: PASS | J9: test/campaign-loop.test.ts
A10: GT-06 | B10: Golden | C10: Campaign lỗ kéo dài (R06B) | D10: R06B | E10: ACoS 70% (> 1.5×BE = 60%), có đơn | F10: Bước 1: MANAGE, $5, bid −20%; bước 2 PAUSE nếu vẫn lỗ; nếu hồi phục thì giữ tag cho R09 | G10: Bước 1 ngày 6, bước 2 ngày 14; biến thể còn lỗ → PAUSED (R06B_PAUSED); biến thể hồi phục → giữ MANAGE | H10: GOLDEN | I10: PASS | J10: test/campaign-loop.test.ts
A11: GT-07 | B11: Regression | C11: R06B kích hoạt lại sau hồi phục | D11: R06B, R09 | E11: ACoS 70% ngày 0–6, 20% ngày 7–40, 70% từ ngày 41; 80 ngày | F11: R06B chạy lại sau khi R09 gỡ tag | G11: R06B ngày 6 và 14; R09 ngày 15; R06B lần hai ngày 56; PAUSE ngày 64 | H11: GOLDEN | I11: PASS | J11: test/campaign-loop.test.ts
A12: GT-08 | B12: Golden (spec Phần 10) | C12: Từ khóa không ra đơn | D12: R12, R13 | E12: Bid $0.80; 20 click/$11.20 rồi thêm 10 click, 0 đơn | F12: R12 −20% + cờ lãng phí; thêm ≥10 click vẫn 0 đơn → R13 PAUSE | G12: R12 ngày 5 ($0.80 → $0.64); R13 ngày 7 PAUSED (30 click, $16.80) | H12: GOLDEN | I12: PASS | J12: test/account-loop.test.ts
A13: A1 | B13: Edge — dữ liệu & thời gian | C13: Bão attribution | D13: R06, R12, R13, R16, R17, R05, R08 | E13: 30% đơn trễ 3–7 ngày + Prime Day làm trễ gấp đôi | F13: Đo số quyết định "0 đơn" bị sai khi dữ liệu chín | G13: 0 quyết định sai (1 seed); Monte Carlo 100 seed cũng 0 | H13: MEASURE | I13: ĐO ĐƯỢC | J13: scenarios/edge/A1.json
A14: A2 | B14: Edge — dữ liệu & thời gian | C14: Đơn bị trả/hủy làm số liệu thay đổi | D14: Tất cả | E14: Có restatement giảm đơn | F14: Mọi quyết định ghi đúng phiên bản tham số và thời điểm dữ liệu; không đọc dữ liệu tương lai | G14: 34 quyết định, 1.444 lần đọc số liệu, 1.787 bản sửa số liệu; không vi phạm | H14: INVARIANT | I14: PASS | J14: scenarios/edge/A2.json
A15: A3 | B15: Edge — dữ liệu & thời gian | C15: Đổi giờ DST (01/11/2026, 14/03/2027) | D15: R20, R21, R21B | E15: Chạy qua 2 ngày đổi giờ | F15: Tổng theo giờ = tổng ngày; mỗi ranh giới giờ ≤ 1 lệnh API | G15: Đúng ở cả 2 ngày; tối đa 1 lệnh/ranh giới | H15: INVARIANT | I15: PASS | J15: scenarios/edge/A3.json
... A41: CTRL-2 | B41: Đối chứng đo lường | C41: Rule theo giờ hoạt động | D41: R20, R21, R21B | E41: Giờ 00 CVR 3%, giờ 01 CVR 45%, 100 ngày | F41: R20 và R21 đều chạy; R21B 1 lệnh/ranh giới | G41: R20 34 lần, R21 33 lần, R21B 626 lệnh, 0 trùng | H41: INVARIANT | I41: PASS | J41: scenarios/edge/hourly-signal.json
A43: =COUNTA(A5:A41) | B43: ← tổng số test case

Sheet Unit test
A1: Toàn bộ unit test của simulator (342 test)
A2: Xuất từ `npx vitest run --reporter=json` ngày 21/10/2026.
A4: File | B4: Nhóm (describe) | C4: Tên test | D4: Trạng thái | E4: Thời gian (ms)
A5: test/account-cli.test.ts | B5: — | C5: CLI --rules all writes account artifacts and target summary | D5: PASS | E5: 3977.8
A6: test/account-edges.test.ts | B6: — | C6: B4 R07 wins same day, R11 skipped then runs on next eligible date; error policy diagnostic | D6: PASS | E6: 61.5
A7: test/account-edges.test.ts | B7: — | C7: B5 waste floor is never raised by R14 during thirty days | D7: PASS | E7: 149
A8: test/account-harvest.test.ts | B8: — | C8: E1 api-chaos invisible creation 20000 minutes: verifies exactly once or times out | D8: PASS | E8: 1464.6
A9: test/account-harvest.test.ts | B9: — | C9: E1 api-chaos invisible creation 5 minutes: verifies exactly once or times out | D9: PASS | E9: 2156.9
A10: test/account-harvest.test.ts | B10: — | C10: E1 failed create leaves no pending state and no negative | D10: PASS | E10: 290.7
A11: test/account-loop.test.ts | B11: — | C11: C4 product price drop below half anchor uses G6 and never sends outside new hard bounds | D11: PASS | E11: 192.7
A12: test/account-loop.test.ts | B12: — | C12: golden zero-order target: day 5 R12, day 7 R13 with hand-computed samples | D12: PASS | E12: 1272.4
A13: test/account-loop.test.ts | B13: — | C13: manual bid edits go through console reconciliation and emit drift | D13: PASS | E13: 61
A14: test/account-loop.test.ts | B14: — | C14: target invariant checks every hourly bid and normalized duplicates | D14: PASS | E14: 7.8
A15: test/account-market.test.ts | B15: — | C15: ScriptedMarket supports exact per-target placements, terms and hourly distribution | D15: PASS | E15: 123.4
A16: test/account-market.test.ts | B16: — | C16: campaign negative removes the matching share across all targets | D16: PASS | E16: 4.6
... A346: test/wrong-zero.test.ts | B346: — | C346: records action delay from the first spend/click threshold day | D346: PASS | E346: 242.4

Sheet Thử nghiệm v3.2
A1: Kết quả thử nghiệm các đề xuất v3.2
A2: Mỗi đề xuất so với v3.1 trên cùng 100 seed Monte Carlo + edge case. Chi tiết: simulator/docs/simulator/v3.2-results.md
A4: Mã | B4: Đề xuất | C4: Vấn đề ở v3.1 | D4: Kết quả đo | E4: Kết luận | F4: Quyết định
A5: P1 | B5: Dùng dữ liệu cũ hơn (D-3/D-5/D-8) cho điều kiện "0 đơn" | C5: Rule "0 đơn" có thể quyết định khi đơn chưa về | D5: Độ trễ bình thường: v3.1 không có quyết định sai; D-8 làm tiền lãng phí $48 → $106, lợi nhuận −$504. Đơn về rất trễ: D-8 chỉ giảm ~30% pause sai | E5: THUA | F5: Không đưa vào v3.2
A6: P2 | B6: R06 thêm điều kiện 14 ngày lịch (không cắt theo reset) | C6: B2: R06 tính thiếu tiền đã đốt | D6: Mọi chỉ số bằng v3.1; R06 vẫn ngày 24 | E6: THẮNG (không xấu đi) | F6: Giữ làm tùy chọn, chưa đưa vào
A7: P3 | B7: R08 chạy hằng ngày | C7: B1: ALERT phụ thuộc ngày bắt đầu lịch | D7: ALERT ngày 18 ở cả 3 pha; không thêm quyết định sai khi bão attribution; đơn về rất trễ: ALERT sai TB 0.15 → 0.18/lượt | E7: THẮNG | F7: Đưa vào v3.2 (kèm lưu ý)
A8: P4 | B8: 7 ngày ân hạn harvest cho campaign nguồn | C8: E6: harvest làm nguồn bị R06 pause | D8: E6 không còn bị pause; tiền lãng phí TB −$8.10; lợi nhuận không đổi | E8: THẮNG | F8: Đưa vào v3.2
A9: P5 | B9: Vùng đệm quanh ngưỡng ACoS | C9: Bid/budget lên xuống liên tục | D9: Số lần đảo chiều chỉ giảm ~8% (mục tiêu 40%) | E9: THUA | F9: Không đưa vào v3.2
A10: P6 | B10: R20/R21 bỏ giờ cạn budget | C10: A5: học hệ số từ giờ thiếu dữ liệu | D10: Hệ số học từ giờ cạn budget: 3 → 0; vẫn phát hiện giờ yếu/mạnh | E10: THẮNG | F10: Đưa vào v3.2
A11: P7 | B11: Sửa câu chữ R04B (~8 ngày lịch) | C11: Spec ghi "mỗi 3 ngày" nhưng thực tế mỗi 8 ngày | D11: Golden: ngày 20 / 28 / 36 | E11: Chỉ sửa câu chữ | F11: Đưa vào v3.2
